CODE_OF_CONDUCT.md
CONTRIBUTING.md
LICENSE
README.rst
setup.cfg
setup.py
docs/changelog.rst
docs/conf.py
docs/index.rst
docs/installation.rst
docs/license.rst
docs/quickstart.rst
docs/static/ast_analyses.png
docs/static/ast_analyses_custom.png
docs/static/ast_analyses_empty.png
docs/static/ast_breakpoints_table.png
docs/static/ast_breakpoints_tables.png
docs/static/ast_panel_custom.png
docs/static/ast_panel_edit.png
docs/static/ast_panel_listing.png
docs/static/identification_analysis.png
docs/static/not_tested.png
docs/static/reject_antibiotics.png
docs/static/selective_reporting.png
src/senaite/__init__.py
src/senaite.ast.egg-info/PKG-INFO
src/senaite.ast.egg-info/SOURCES.txt
src/senaite.ast.egg-info/dependency_links.txt
src/senaite.ast.egg-info/entry_points.txt
src/senaite.ast.egg-info/namespace_packages.txt
src/senaite.ast.egg-info/not-zip-safe
src/senaite.ast.egg-info/requires.txt
src/senaite.ast.egg-info/top_level.txt
src/senaite/ast/__init__.py
src/senaite/ast/calc.py
src/senaite/ast/config.py
src/senaite/ast/configure.zcml
src/senaite/ast/datamanagers.py
src/senaite/ast/i18n.py
src/senaite/ast/interfaces.py
src/senaite/ast/permissions.py
src/senaite/ast/permissions.zcml
src/senaite/ast/setuphandlers.py
src/senaite/ast/utils.py
src/senaite/ast/vocabularies.py
src/senaite/ast/adapters/__init__.py
src/senaite/ast/adapters/configure.zcml
src/senaite/ast/adapters/form.py
src/senaite/ast/adapters/guards.py
src/senaite/ast/adapters/listing/__init__.py
src/senaite/ast/adapters/listing/analysisrequest.py
src/senaite/ast/adapters/listing/antibiotics.py
src/senaite/ast/adapters/listing/astpanel.py
src/senaite/ast/adapters/listing/services.py
src/senaite/ast/adapters/listing/worksheet.py
src/senaite/ast/behaviors/__init__.py
src/senaite/ast/behaviors/abx.py
src/senaite/ast/behaviors/astpanel.py
src/senaite/ast/behaviors/breakpointstable.py
src/senaite/ast/behaviors/configure.zcml
src/senaite/ast/browser/__init__.py
src/senaite/ast/browser/addpanel.py
src/senaite/ast/browser/configure.zcml
src/senaite/ast/browser/duplicateview.py
src/senaite/ast/browser/panel.py
src/senaite/ast/browser/reporting.py
src/senaite/ast/browser/results.py
src/senaite/ast/browser/content/__init__.py
src/senaite/ast/browser/content/astpanelfolder.py
src/senaite/ast/browser/content/breakpointstables.py
